notelink/__init__.py
notelink/configs.py
notelink/main.py
notelink/core/__init__.py
notelink/core/helpers.py
notelink/promps/__init__.py
notelink/promps/list.py
notelink/promps/search.py
notelink-0.0.5.dist-info/METADATA
notelink-0.0.5.dist-info/WHEEL
notelink-0.0.5.dist-info/entry_points.txt
notelink-0.0.5.dist-info/top_level.txt
notelink-0.0.5.dist-info/RECORD
