Metadata-Version: 2.1
Name: notelink
Version: 0.0.5
Summary: Management your favorite link using CLI.
Home-page: https://github.com/agung96tm/notelink
Author: Agung Yuliyanto
Author-email: agung.96tm@gmail.com
License: MIT
Project-URL: Documentation, https://github.com/agung96tm/notelink
Project-URL: Source Code, https://github.com/agung96tm/notelink
Project-URL: Issue Tracker, https://github.com/agung96tm/notelink/issues/
Platform: UNKNOWN
Classifier: Intended Audience :: Education
Classifier: Intended Audience :: Developers
Classifier: Programming Language :: Python :: 3
Classifier: Operating System :: OS Independent
Requires-Python: >=3.6
Requires-Dist: click (<9.0.0,>=8.0.1)
Requires-Dist: inquirer (<3.0.0,>=2.7.0)
Requires-Dist: configobj (<6.0.0,>=5.0.6)
